mpl_markers/__init__.py
mpl_markers/artists.py
mpl_markers/interactive.py
mpl_markers/markers.py
mpl_markers/utils.py
mpl_markers/style/default.json
mpl_markers-0.0.21.dist-info/licenses/LICENSE.txt
mpl_markers-0.0.21.dist-info/METADATA
mpl_markers-0.0.21.dist-info/WHEEL
mpl_markers-0.0.21.dist-info/top_level.txt
mpl_markers-0.0.21.dist-info/RECORD
